bert_experimental/__init__.py
bert_experimental/feature_extraction/__init__.py
bert_experimental/feature_extraction/bert_feature_extractor.py
bert_experimental/feature_extraction/l2_retriever.py
bert_experimental/feature_extraction/text_preprocessing.py
bert_experimental/finetuning/__init__.py
bert_experimental/finetuning/bert_layer.py
bert_experimental/finetuning/graph_ops.py
bert_experimental/finetuning/modeling.py
bert_experimental/finetuning/text_preprocessing.py
bert_experimental-1.0.5.dist-info/LICENSE
bert_experimental-1.0.5.dist-info/METADATA
bert_experimental-1.0.5.dist-info/WHEEL
bert_experimental-1.0.5.dist-info/top_level.txt
bert_experimental-1.0.5.dist-info/RECORD
