Metadata-Version: 2.1
Name: bert-experimental
Version: 1.0.5
Summary: Utilities for finetuning BERT-like models
Home-page: https://github.com/gaphex/bert_experimental
Author: Denis Antyukhov
Author-email: gaphex@gmail.com
License: MIT
Keywords: bert nlp tensorflow machine learning sentence encoding embedding finetuning
Platform: UNKNOWN
Classifier: Programming Language :: Python :: 3.7
Classifier: License :: OSI Approved :: MIT License
Classifier: Operating System :: OS Independent
Classifier: Topic :: Scientific/Engineering :: Artificial Intelligence
Requires-Dist: tensorflow (<2.0,>=1.15)
Requires-Dist: tensorflow-hub (==0.7.0)
Requires-Dist: numpy
